twitographer/__init__.py
twitographer/credentials.py
twitographer-1.0.0.dist-info/METADATA
twitographer-1.0.0.dist-info/RECORD
twitographer-1.0.0.dist-info/WHEEL
twitographer-1.0.0.dist-info/top_level.txt
