Metadata-Version: 2.1
Name: twitographer
Version: 1.0.0
Summary: A parallelized web crawler to traverse the Twitter graph
Home-page: https://github.com/liveb33f/twitographer
Author: liveb33f
Author-email: livebeef@protonmail.com
License: unlicense
Platform: UNKNOWN
Classifier: Programming Language :: Python :: 3
Classifier: License :: Public Domain
Requires-Dist: pyppeteer
Requires-Dist: redis
